blog/__init__.py
blog/admin.py
blog/apps.py
blog/models.py
blog/tests.py
blog/urls.py
blog/views.py
blog/migrations/0001_initial.py
blog/migrations/__init__.py
django_markdown_blog-0.4.dist-info/DESCRIPTION.rst
django_markdown_blog-0.4.dist-info/METADATA
django_markdown_blog-0.4.dist-info/RECORD
django_markdown_blog-0.4.dist-info/WHEEL
django_markdown_blog-0.4.dist-info/metadata.json
django_markdown_blog-0.4.dist-info/top_level.txt
