Metadata-Version: 2.0
Name: django-markdown-blog
Version: 0.4
Summary: A simple Django app to provide markdown blog functionality.
Home-page: UNKNOWN
Author: Kevin Mann
Author-email: kevinrmann@gmail.com
License: BSD License
Platform: UNKNOWN
Classifier: Environment :: Web Environment
Classifier: Framework :: Django
Classifier: Framework :: Django :: 1.10
Classifier: Intended Audience :: Developers
Classifier: License :: OSI Approved :: MIT License
Classifier: Operating System :: OS Independent
Classifier: Programming Language :: Python
Classifier: Programming Language :: Python :: 2
Classifier: Programming Language :: Python :: 3
Classifier: Programming Language :: Python :: 3.4
Classifier: Programming Language :: Python :: 3.5
Classifier: Topic :: Internet :: WWW/HTTP
Classifier: Topic :: Internet :: WWW/HTTP :: Dynamic Content
Requires-Dist: Django (>=1.9)
Requires-Dist: awesome-slugify (>=1.6.5)
Requires-Dist: django-autoslug (>=1.9.3)
Requires-Dist: django-imagekit (>=3.3)
Requires-Dist: django-markdown-app (>=0.9.0)
